general_calculator_zsd/__init__.py
general_calculator_zsd/general_calculator.py
general_calculator_zsd/general_parameter.py
general_calculator_zsd/mysql_transmit_data4all.py
general_calculator_zsd-1.9.1.dist-info/licenses/LICENSE
general_calculator_zsd-1.9.1.dist-info/METADATA
general_calculator_zsd-1.9.1.dist-info/WHEEL
general_calculator_zsd-1.9.1.dist-info/top_level.txt
general_calculator_zsd-1.9.1.dist-info/RECORD
