Metadata-Version: 2.4
Name: general_calculator_zsd
Version: 1.9.1
Summary: 数据采集专用通用脚本
Author-email: Colin Zhang <zsd0830@163.com>
Classifier: Programming Language :: Python :: 3
Classifier: License :: OSI Approved :: MIT License
Classifier: Operating System :: OS Independent
Requires-Python: >=3.8
License-File: LICENSE
Dynamic: license-file
